sphinx_boogergreen_theme/__init__.py
sphinx_boogergreen_theme/breadcrumbs.html
sphinx_boogergreen_theme/footer.html
sphinx_boogergreen_theme/layout.html
sphinx_boogergreen_theme/search.html
sphinx_boogergreen_theme/searchbox.html
sphinx_boogergreen_theme/theme.conf
sphinx_boogergreen_theme/versions.html
sphinx_boogergreen_theme/static/css/badge_only.css
sphinx_boogergreen_theme/static/css/theme.css
sphinx_boogergreen_theme/static/fonts/fontawesome-webfont.eot
sphinx_boogergreen_theme/static/fonts/fontawesome-webfont.svg
sphinx_boogergreen_theme/static/fonts/fontawesome-webfont.ttf
sphinx_boogergreen_theme/static/fonts/fontawesome-webfont.woff
sphinx_boogergreen_theme/static/fonts/fontawesome-webfont.woff2
sphinx_boogergreen_theme/static/js/modernizr.min.js
sphinx_boogergreen_theme/static/js/theme.js
sphinx_boogergreen_theme-0.4.3.dist-info/LICENSE
sphinx_boogergreen_theme-0.4.3.dist-info/METADATA
sphinx_boogergreen_theme-0.4.3.dist-info/WHEEL
sphinx_boogergreen_theme-0.4.3.dist-info/entry_points.txt
sphinx_boogergreen_theme-0.4.3.dist-info/top_level.txt
sphinx_boogergreen_theme-0.4.3.dist-info/RECORD
